onto/__init__.py
onto/admin.py
onto/apps.py
onto/authz/__init__.py
onto/authz/admin.py
onto/authz/apps.py
onto/authz/migrations/0001_initial.py
onto/authz/migrations/__init__.py
onto/authz/models.py
onto/authz/signals.py
onto/authz/utils.py
onto/migrations/0001_initial.py
onto/migrations/__init__.py
onto/models.py
onto/signals.py
onto/tests.py
onto/utils.py
onto/views.py
django_onto-0.1.1.dist-info/WHEEL
django_onto-0.1.1.dist-info/LICENSE
django_onto-0.1.1.dist-info/METADATA
django_onto-0.1.1.dist-info/RECORD
